setup.py
commons/__init__.py
commons/auth.py
commons/business.py
commons/persistence.py
meiupp_commons.egg-info/PKG-INFO
meiupp_commons.egg-info/SOURCES.txt
meiupp_commons.egg-info/dependency_links.txt
meiupp_commons.egg-info/top_level.txt
test/test_persistence.py