Metadata-Version: 1.0
Name: meiupp-commons
Version: 0.0.13
Summary: common code
Home-page: https://bitbucket.org/meiupp/commons
Author: UNKNOWN
Author-email: UNKNOWN
License: UNKNOWN
Platform: UNKNOWN
